README.md
setup.cfg
setup.py
motionConstrain/__init__.py
motionConstrain/motionConstrain.py
motionConstrain/motionConstrainSolver.py
motionConstrain/postProcessBSF.py
motionConstrain.egg-info/PKG-INFO
motionConstrain.egg-info/SOURCES.txt
motionConstrain.egg-info/dependency_links.txt
motionConstrain.egg-info/requires.txt
motionConstrain.egg-info/top_level.txt