Metadata-Version: 1.1
Name: motionConstrain
Version: 5.0.9
Summary: spatial constraint (incompressible)
Home-page: https://github.com/JorryZ/motionConstrain
Author: Yu Zheng
Author-email: jorry.zhengyu@gmail.com
License: MIT
Download-URL: https://github.com/JorryZ/motionConstrain/archive/v5.0.9.tar.gz
Keywords: explicit,motion,incompressibility,regularization
Platform: UNKNOWN
Classifier: Development Status :: 5 - Production/Stable
Classifier: Intended Audience :: Developers
Classifier: Topic :: Software Development :: Build Tools
Classifier: License :: OSI Approved :: MIT License
Classifier: Programming Language :: Python :: 3.6
Classifier: Programming Language :: Python :: 3.7
